metamorphosis.so
ndreg/__init__.py
ndreg/__version__.py
ndreg/ndreg.py
ndreg/plotter.py
ndreg/preprocessor.py
ndreg/util.py
ndreg-1.0.0.dist-info/METADATA
ndreg-1.0.0.dist-info/RECORD
ndreg-1.0.0.dist-info/WHEEL
ndreg-1.0.0.dist-info/top_level.txt
