Metadata-Version: 2.1
Name: ndreg
Version: 1.0.0
Summary: Registration package that does affine and LDDMM registration
Home-page: https://github.com/neurodata/ndreg
Author: Vikram Chandrashekhar
Author-email: vikramc@jhmi.edu
License: MIT
Platform: UNKNOWN
Classifier: License :: OSI Approved :: MIT License
Classifier: Programming Language :: Python
Classifier: Programming Language :: Python :: 2.6
Classifier: Programming Language :: Python :: 2.7
Classifier: Programming Language :: Python :: 3
Classifier: Programming Language :: Python :: 3.3
Classifier: Programming Language :: Python :: 3.4
Classifier: Programming Language :: Python :: 3.5
Classifier: Programming Language :: Python :: 3.6
Classifier: Programming Language :: Python :: Implementation :: CPython
Classifier: Programming Language :: Python :: Implementation :: PyPy
Requires-Dist: requests
Requires-Dist: numpy
Requires-Dist: SimpleITK
Requires-Dist: scikit-image
Requires-Dist: tifffile
Requires-Dist: scikit-image
